LICENSE
MANIFEST.in
README.rst
setup.py
license/__init__.py
license/base.py
license/core.py
license/licenses.py
license.egg-info/PKG-INFO
license.egg-info/SOURCES.txt
license.egg-info/dependency_links.txt
license.egg-info/requires.txt
license.egg-info/top_level.txt
license/templates/AGPL-3.0
license/templates/AGPL-3.0+
license/templates/AGPL-3.0+__header
license/templates/AGPL-3.0__header
license/templates/BSD-2-Clause
license/templates/BSD-3-Clause
license/templates/GPL-2.0
license/templates/GPL-2.0+
license/templates/GPL-2.0+__header
license/templates/GPL-2.0__header
license/templates/GPL-3.0
license/templates/GPL-3.0+
license/templates/GPL-3.0+__header
license/templates/GPL-3.0__header
license/templates/LGPL-2.1
license/templates/LGPL-2.1+
license/templates/LGPL-2.1+__header
license/templates/LGPL-2.1__header
license/templates/LGPL-3.0
license/templates/LGPL-3.0+
license/templates/LGPL-3.0+__header
license/templates/LGPL-3.0__header
license/templates/MIT
test/__init__.py
test/test_base.py
test/test_db.py
test/test_render.py
test/files/CUSTOM